funcoin/__init__.py
funcoin/base/__init__.py
funcoin/base/db/__init__.py
funcoin/base/db/base.py
funcoin/base/drive/__init__.py
funcoin/base/drive/job.py
funcoin/base/drive/lanzou.py
funcoin/base/drive/oss.py
funcoin/base/drive/transform.py
funcoin/base/tables/__init__.py
funcoin/base/tables/kline.py
funcoin/base/tables/strategy.py
funcoin/base/tables/trade.py
funcoin/coins/__init__.py
funcoin/coins/base/__init__.py
funcoin/coins/base/file.py
funcoin/coins/base/load.py
funcoin/coins/okex/__init__.py
funcoin/coins/okex/load.py
funcoin/server/__init__.py
funcoin/server/download.py
funcoin/server/notecoin_celery.py
funcoin/server/notecoin_server.py
funcoin/server/script.py
funcoin/server/strategy.py
funcoin/server/connect/__init__.py
funcoin/server/connect/base.py
funcoin/strategy/__init__.py
funcoin/strategy/binance/__init__.py
funcoin/strategy/binance/auto.py
funcoin/strategy/binance/example2.py
funcoin/strategy/binance/strategy1.py
funcoin/strategy/binance/strategy2.py
funcoin/task/__init__.py
funcoin/task/base.py
funcoin/task/load.py
funcoin/utils/__init__.py
funcoin/utils/log.py
funcoin/utils/time.py
funcoin-202308241628.dist-info/LICENSE
funcoin-202308241628.dist-info/METADATA
funcoin-202308241628.dist-info/WHEEL
funcoin-202308241628.dist-info/entry_points.txt
funcoin-202308241628.dist-info/top_level.txt
funcoin-202308241628.dist-info/RECORD
