Metadata-Version: 2.1
Name: funcoin
Version: 202308241628
Summary: funcoin
Home-page: https://github.com/1007530194
Author: bingtao
Author-email: 1007530194@qq.com
License-File: LICENSE
Requires-Dist: funbuild
Requires-Dist: funsecret
Requires-Dist: funfile
Requires-Dist: pymysql
Requires-Dist: ccxt
